{
    "17_742_18.png1112147": {
        "filename": "17_742_18.png",
        "size": 1112147,
        "file_attributes": {},
        "regions": [
            {
                "shape_attributes": {
                    "name": "polyline",
                    "all_points_x": [
                        663,
                        635,
                        608,
                        583,
                        559,
                        534,
                        506,
                        481,
                        451,
                        422,
                        397,
                        369,
                        347,
                        331,
                        307,
                        283,
                        260,
                        239,
                        219,
                        201,
                        176,
                        154,
                        132,
                        112,
                        94,
                        78,
                        65,
                        60,
                        66,
                        77,
                        91,
                        105,
                        120,
                        137,
                        155,
                        173,
                        191,
                        209,
                        228,
                        249,
                        272,
                        301,
                        328,
                        355,
                        384,
                        413,
                        441,
                        467,
                        495,
                        525,
                        553,
                        569,
                        593,
                        612,
                        639,
                        667,
                        694,
                        720,
                        748,
                        773,
                        798,
                        818,
                        839,
                        865,
                        890,
                        907,
                        926,
                        955,
                        983,
                        1010,
                        1036,
                        1062,
                        1086,
                        1106,
                        1123,
                        1137,
                        1151,
                        1164,
                        1174,
                        1177,
                        1165,
                        1150,
                        1133,
                        1111,
                        1091,
                        1067,
                        1045,
                        1024,
                        999,
                        978,
                        955,
                        930,
                        908,
                        881,
                        854,
                        827,
                        800,
                        773,
                        755,
                        733,
                        711,
                        687,
                        663
                    ],
                    "all_points_y": [
                        549,
                        547,
                        544,
                        541,
                        531,
                        522,
                        526,
                        532,
                        533,
                        532,
                        529,
                        523,
                        523,
                        509,
                        499,
                        489,
                        478,
                        465,
                        451,
                        435,
                        426,
                        414,
                        402,
                        388,
                        372,
                        354,
                        333,
                        304,
                        278,
                        255,
                        234,
                        214,
                        196,
                        178,
                        163,
                        147,
                        130,
                        115,
                        100,
                        86,
                        76,
                        70,
                        63,
                        60,
                        63,
                        62,
                        60,
                        62,
                        65,
                        68,
                        70,
                        88,
                        94,
                        80,
                        84,
                        90,
                        93,
                        99,
                        97,
                        100,
                        105,
                        119,
                        114,
                        106,
                        101,
                        118,
                        133,
                        138,
                        142,
                        149,
                        153,
                        161,
                        171,
                        185,
                        202,
                        222,
                        242,
                        263,
                        287,
                        315,
                        337,
                        357,
                        373,
                        385,
                        399,
                        408,
                        420,
                        432,
                        440,
                        452,
                        462,
                        468,
                        480,
                        486,
                        493,
                        497,
                        498,
                        498,
                        513,
                        523,
                        535,
                        541,
                        549
                    ]
                },
                "region_attributes": {}
            }
        ]
    }
}