{
    "17_731_32.png781336": {
        "filename": "17_731_32.png",
        "size": 781336,
        "file_attributes": {},
        "regions": [
            {
                "shape_attributes": {
                    "name": "polyline",
                    "all_points_x": [
                        218,
                        106,
                        85,
                        74,
                        90,
                        158,
                        291,
                        403,
                        488,
                        559,
                        642,
                        710,
                        801,
                        918,
                        957,
                        986,
                        1001,
                        999,
                        988,
                        962,
                        892,
                        806,
                        736,
                        681,
                        647,
                        551,
                        449,
                        379,
                        280,
                        218
                    ],
                    "all_points_y": [
                        156,
                        247,
                        296,
                        333,
                        385,
                        411,
                        424,
                        406,
                        406,
                        400,
                        377,
                        385,
                        408,
                        424,
                        424,
                        406,
                        374,
                        320,
                        281,
                        260,
                        226,
                        195,
                        163,
                        161,
                        161,
                        130,
                        114,
                        114,
                        127,
                        156
                    ]
                },
                "region_attributes": {}
            }
        ]
    }
}