{
    "18_746_381.png3250913": {
        "filename": "18_746_381.png",
        "size": 3250913,
        "file_attributes": {},
        "regions": [
            {
                "shape_attributes": {
                    "name": "polyline",
                    "all_points_x": [
                        1055,
                        1006,
                        957,
                        914,
                        864,
                        821,
                        772,
                        728,
                        675,
                        621,
                        574,
                        531,
                        492,
                        455,
                        405,
                        355,
                        300,
                        245,
                        190,
                        134,
                        94,
                        68,
                        60,
                        83,
                        114,
                        143,
                        172,
                        203,
                        234,
                        268,
                        304,
                        341,
                        379,
                        416,
                        455,
                        495,
                        535,
                        584,
                        628,
                        665,
                        722,
                        774,
                        827,
                        878,
                        935,
                        992,
                        1042,
                        1084,
                        1119,
                        1168,
                        1211,
                        1246,
                        1294,
                        1345,
                        1395,
                        1444,
                        1490,
                        1540,
                        1594,
                        1641,
                        1693,
                        1751,
                        1798,
                        1846,
                        1891,
                        1933,
                        1982,
                        2027,
                        2065,
                        2107,
                        2145,
                        2179,
                        2208,
                        2224,
                        2213,
                        2184,
                        2171,
                        2133,
                        2083,
                        2031,
                        1979,
                        1930,
                        1879,
                        1828,
                        1773,
                        1720,
                        1668,
                        1625,
                        1580,
                        1529,
                        1479,
                        1426,
                        1378,
                        1329,
                        1319,
                        1296,
                        1260,
                        1220,
                        1178,
                        1131,
                        1085
                    ],
                    "all_points_y": [
                        852,
                        843,
                        833,
                        821,
                        811,
                        797,
                        811,
                        817,
                        812,
                        802,
                        785,
                        764,
                        741,
                        714,
                        702,
                        694,
                        685,
                        678,
                        671,
                        663,
                        639,
                        601,
                        550,
                        509,
                        477,
                        442,
                        407,
                        373,
                        340,
                        311,
                        282,
                        255,
                        229,
                        202,
                        177,
                        153,
                        129,
                        122,
                        114,
                        88,
                        80,
                        80,
                        69,
                        62,
                        59,
                        64,
                        78,
                        98,
                        127,
                        118,
                        131,
                        150,
                        136,
                        133,
                        145,
                        156,
                        168,
                        169,
                        176,
                        193,
                        203,
                        209,
                        222,
                        238,
                        257,
                        279,
                        294,
                        313,
                        337,
                        359,
                        385,
                        415,
                        448,
                        493,
                        540,
                        572,
                        609,
                        634,
                        644,
                        650,
                        654,
                        655,
                        648,
                        639,
                        632,
                        625,
                        623,
                        642,
                        659,
                        666,
                        672,
                        665,
                        659,
                        662,
                        711,
                        749,
                        778,
                        802,
                        823,
                        835,
                        844
                    ]
                },
                "region_attributes": {}
            }
        ]
    }
}