{
    "18_746_551.png1428219": {
        "filename": "18_746_551.png",
        "size": 1428219,
        "file_attributes": {},
        "regions": [
            {
                "shape_attributes": {
                    "name": "polyline",
                    "all_points_x": [
                        515,
                        486,
                        461,
                        434,
                        409,
                        385,
                        362,
                        342,
                        328,
                        304,
                        284,
                        261,
                        238,
                        213,
                        187,
                        162,
                        139,
                        115,
                        94,
                        75,
                        62,
                        69,
                        75,
                        86,
                        103,
                        112,
                        129,
                        148,
                        167,
                        187,
                        210,
                        232,
                        249,
                        269,
                        299,
                        327,
                        355,
                        382,
                        415,
                        452,
                        484,
                        515,
                        546,
                        576,
                        605,
                        632,
                        653,
                        682,
                        708,
                        728,
                        760,
                        790,
                        819,
                        841,
                        867,
                        895,
                        921,
                        948,
                        972,
                        989,
                        1010,
                        1036,
                        1067,
                        1097,
                        1125,
                        1153,
                        1174,
                        1194,
                        1213,
                        1233,
                        1252,
                        1269,
                        1280,
                        1285,
                        1277,
                        1262,
                        1241,
                        1217,
                        1191,
                        1165,
                        1137,
                        1105,
                        1074,
                        1038,
                        1005,
                        973,
                        945,
                        919,
                        892,
                        864,
                        836,
                        807,
                        778,
                        749,
                        719,
                        689,
                        660,
                        632,
                        606,
                        578,
                        551,
                        521
                    ],
                    "all_points_y": [
                        599,
                        591,
                        587,
                        579,
                        567,
                        554,
                        542,
                        525,
                        502,
                        489,
                        472,
                        458,
                        444,
                        432,
                        421,
                        411,
                        397,
                        384,
                        368,
                        350,
                        326,
                        299,
                        269,
                        243,
                        222,
                        199,
                        179,
                        161,
                        143,
                        126,
                        113,
                        100,
                        83,
                        66,
                        64,
                        64,
                        66,
                        62,
                        62,
                        62,
                        63,
                        67,
                        73,
                        80,
                        86,
                        96,
                        112,
                        116,
                        127,
                        144,
                        147,
                        152,
                        156,
                        171,
                        178,
                        187,
                        192,
                        182,
                        191,
                        211,
                        227,
                        238,
                        244,
                        251,
                        260,
                        267,
                        283,
                        300,
                        318,
                        335,
                        353,
                        373,
                        399,
                        429,
                        458,
                        480,
                        496,
                        508,
                        520,
                        530,
                        540,
                        545,
                        546,
                        547,
                        547,
                        548,
                        553,
                        564,
                        574,
                        573,
                        583,
                        582,
                        581,
                        584,
                        581,
                        580,
                        577,
                        580,
                        590,
                        595,
                        595,
                        597
                    ]
                },
                "region_attributes": {}
            }
        ]
    }
}