{
    "18_746_469.png2270495": {
        "filename": "18_746_469.png",
        "size": 2270495,
        "file_attributes": {},
        "regions": [
            {
                "shape_attributes": {
                    "name": "polyline",
                    "all_points_x": [
                        210,
                        164,
                        122,
                        88,
                        65,
                        65,
                        83,
                        110,
                        130,
                        156,
                        180,
                        205,
                        226,
                        250,
                        276,
                        302,
                        327,
                        354,
                        385,
                        416,
                        448,
                        479,
                        509,
                        548,
                        587,
                        624,
                        669,
                        707,
                        752,
                        795,
                        842,
                        883,
                        926,
                        968,
                        1016,
                        1058,
                        1097,
                        1135,
                        1181,
                        1223,
                        1256,
                        1294,
                        1334,
                        1373,
                        1407,
                        1445,
                        1487,
                        1528,
                        1568,
                        1607,
                        1644,
                        1679,
                        1713,
                        1747,
                        1770,
                        1795,
                        1819,
                        1845,
                        1864,
                        1867,
                        1848,
                        1820,
                        1786,
                        1749,
                        1706,
                        1657,
                        1607,
                        1562,
                        1521,
                        1483,
                        1445,
                        1407,
                        1371,
                        1329,
                        1286,
                        1242,
                        1200,
                        1161,
                        1117,
                        1097,
                        1067,
                        1034,
                        995,
                        951,
                        909,
                        867,
                        837,
                        802,
                        764,
                        726,
                        683,
                        640,
                        594,
                        543,
                        496,
                        448,
                        406,
                        362,
                        321,
                        277,
                        230
                    ],
                    "all_points_y": [
                        692,
                        690,
                        680,
                        660,
                        629,
                        587,
                        555,
                        528,
                        494,
                        465,
                        436,
                        406,
                        374,
                        344,
                        316,
                        288,
                        258,
                        232,
                        208,
                        186,
                        163,
                        140,
                        116,
                        101,
                        94,
                        77,
                        70,
                        64,
                        66,
                        62,
                        69,
                        80,
                        84,
                        93,
                        95,
                        97,
                        106,
                        110,
                        114,
                        122,
                        143,
                        155,
                        163,
                        174,
                        194,
                        210,
                        222,
                        235,
                        249,
                        264,
                        281,
                        300,
                        320,
                        340,
                        371,
                        400,
                        430,
                        458,
                        493,
                        536,
                        570,
                        596,
                        617,
                        633,
                        642,
                        641,
                        639,
                        630,
                        617,
                        601,
                        585,
                        569,
                        551,
                        539,
                        528,
                        526,
                        520,
                        517,
                        519,
                        552,
                        576,
                        594,
                        605,
                        607,
                        595,
                        590,
                        613,
                        632,
                        644,
                        657,
                        659,
                        656,
                        664,
                        667,
                        666,
                        666,
                        670,
                        679,
                        683,
                        685,
                        689
                    ]
                },
                "region_attributes": {}
            }
        ]
    }
}