{
    "18_746_340.png2252613": {
        "filename": "18_746_340.png",
        "size": 2252613,
        "file_attributes": {},
        "regions": [
            {
                "shape_attributes": {
                    "name": "polyline",
                    "all_points_x": [
                        791,
                        750,
                        708,
                        667,
                        626,
                        585,
                        543,
                        501,
                        457,
                        408,
                        362,
                        318,
                        275,
                        228,
                        185,
                        146,
                        112,
                        85,
                        65,
                        63,
                        78,
                        102,
                        126,
                        152,
                        184,
                        215,
                        243,
                        259,
                        273,
                        291,
                        316,
                        344,
                        369,
                        404,
                        435,
                        471,
                        514,
                        548,
                        590,
                        639,
                        685,
                        728,
                        774,
                        822,
                        866,
                        910,
                        952,
                        997,
                        1036,
                        1081,
                        1124,
                        1160,
                        1196,
                        1237,
                        1281,
                        1325,
                        1362,
                        1389,
                        1410,
                        1450,
                        1484,
                        1518,
                        1558,
                        1598,
                        1634,
                        1665,
                        1699,
                        1729,
                        1757,
                        1783,
                        1806,
                        1831,
                        1849,
                        1849,
                        1828,
                        1802,
                        1767,
                        1728,
                        1685,
                        1644,
                        1600,
                        1557,
                        1514,
                        1472,
                        1432,
                        1392,
                        1347,
                        1305,
                        1267,
                        1229,
                        1188,
                        1145,
                        1104,
                        1082,
                        1067,
                        1040,
                        1011,
                        976,
                        936,
                        898,
                        856,
                        810
                    ],
                    "all_points_y": [
                        702,
                        698,
                        695,
                        691,
                        681,
                        669,
                        658,
                        647,
                        642,
                        646,
                        647,
                        649,
                        649,
                        644,
                        634,
                        620,
                        601,
                        575,
                        542,
                        498,
                        461,
                        432,
                        405,
                        379,
                        358,
                        336,
                        312,
                        290,
                        264,
                        253,
                        225,
                        199,
                        173,
                        155,
                        134,
                        116,
                        110,
                        91,
                        80,
                        77,
                        69,
                        63,
                        62,
                        65,
                        74,
                        81,
                        90,
                        96,
                        110,
                        108,
                        112,
                        129,
                        146,
                        154,
                        157,
                        166,
                        175,
                        178,
                        188,
                        193,
                        212,
                        231,
                        244,
                        257,
                        274,
                        296,
                        315,
                        338,
                        363,
                        390,
                        420,
                        448,
                        483,
                        528,
                        559,
                        586,
                        605,
                        619,
                        624,
                        632,
                        637,
                        635,
                        625,
                        614,
                        603,
                        598,
                        590,
                        579,
                        564,
                        549,
                        539,
                        533,
                        544,
                        575,
                        608,
                        635,
                        656,
                        673,
                        685,
                        692,
                        697,
                        700
                    ]
                },
                "region_attributes": {}
            }
        ]
    }
}