{
    "18_746_165.png2169301": {
        "filename": "18_746_165.png",
        "size": 2169301,
        "file_attributes": {},
        "regions": [
            {
                "shape_attributes": {
                    "name": "polyline",
                    "all_points_x": [
                        560,
                        525,
                        487,
                        456,
                        431,
                        404,
                        382,
                        359,
                        327,
                        288,
                        252,
                        213,
                        173,
                        133,
                        101,
                        78,
                        64,
                        60,
                        67,
                        83,
                        105,
                        127,
                        157,
                        182,
                        203,
                        225,
                        250,
                        274,
                        301,
                        332,
                        370,
                        393,
                        428,
                        468,
                        510,
                        546,
                        583,
                        619,
                        658,
                        698,
                        738,
                        774,
                        808,
                        840,
                        878,
                        911,
                        941,
                        973,
                        1011,
                        1044,
                        1082,
                        1127,
                        1165,
                        1201,
                        1240,
                        1279,
                        1315,
                        1353,
                        1388,
                        1424,
                        1455,
                        1481,
                        1507,
                        1536,
                        1566,
                        1595,
                        1620,
                        1637,
                        1643,
                        1629,
                        1611,
                        1590,
                        1560,
                        1524,
                        1487,
                        1448,
                        1411,
                        1373,
                        1335,
                        1298,
                        1259,
                        1220,
                        1183,
                        1146,
                        1107,
                        1069,
                        1031,
                        1009,
                        975,
                        947,
                        918,
                        887,
                        854,
                        826,
                        802,
                        774,
                        742,
                        708,
                        673,
                        636,
                        597
                    ],
                    "all_points_y": [
                        756,
                        745,
                        733,
                        716,
                        691,
                        668,
                        640,
                        613,
                        597,
                        592,
                        584,
                        579,
                        572,
                        565,
                        547,
                        520,
                        484,
                        446,
                        409,
                        375,
                        347,
                        319,
                        299,
                        273,
                        244,
                        217,
                        192,
                        165,
                        142,
                        123,
                        117,
                        92,
                        81,
                        77,
                        73,
                        59,
                        64,
                        64,
                        65,
                        69,
                        77,
                        91,
                        101,
                        119,
                        129,
                        146,
                        153,
                        170,
                        178,
                        195,
                        201,
                        202,
                        212,
                        226,
                        217,
                        228,
                        240,
                        252,
                        267,
                        281,
                        300,
                        324,
                        348,
                        369,
                        389,
                        410,
                        435,
                        468,
                        509,
                        546,
                        576,
                        604,
                        624,
                        638,
                        645,
                        646,
                        637,
                        629,
                        619,
                        613,
                        605,
                        600,
                        593,
                        600,
                        593,
                        587,
                        583,
                        607,
                        622,
                        603,
                        594,
                        613,
                        630,
                        652,
                        678,
                        700,
                        719,
                        731,
                        745,
                        752,
                        753
                    ]
                },
                "region_attributes": {}
            }
        ]
    }
}