{
    "19_760_38.png3568508": {
        "filename": "19_760_38.png",
        "size": 3568508,
        "file_attributes": {},
        "regions": [
            {
                "shape_attributes": {
                    "name": "polyline",
                    "all_points_x": [
                        382,
                        318,
                        253,
                        192,
                        127,
                        68,
                        30,
                        33,
                        63,
                        94,
                        126,
                        160,
                        195,
                        229,
                        262,
                        297,
                        325,
                        359,
                        398,
                        441,
                        486,
                        530,
                        573,
                        616,
                        660,
                        702,
                        754,
                        805,
                        863,
                        923,
                        981,
                        1044,
                        1105,
                        1163,
                        1221,
                        1276,
                        1319,
                        1375,
                        1424,
                        1467,
                        1523,
                        1581,
                        1629,
                        1682,
                        1735,
                        1786,
                        1844,
                        1903,
                        1941,
                        1989,
                        2038,
                        2088,
                        2140,
                        2193,
                        2243,
                        2292,
                        2336,
                        2377,
                        2417,
                        2455,
                        2487,
                        2524,
                        2542,
                        2521,
                        2480,
                        2431,
                        2375,
                        2320,
                        2261,
                        2201,
                        2152,
                        2100,
                        2039,
                        1979,
                        1924,
                        1864,
                        1803,
                        1778,
                        1720,
                        1659,
                        1600,
                        1543,
                        1497,
                        1443,
                        1390,
                        1335,
                        1271,
                        1205,
                        1148,
                        1097,
                        1040,
                        980,
                        915,
                        850,
                        790,
                        730,
                        670,
                        607,
                        549,
                        488,
                        429
                    ],
                    "all_points_y": [
                        924,
                        922,
                        915,
                        904,
                        895,
                        884,
                        848,
                        789,
                        745,
                        701,
                        660,
                        620,
                        581,
                        540,
                        499,
                        461,
                        415,
                        374,
                        339,
                        309,
                        279,
                        249,
                        218,
                        187,
                        157,
                        125,
                        105,
                        90,
                        80,
                        71,
                        62,
                        63,
                        66,
                        72,
                        86,
                        105,
                        136,
                        130,
                        155,
                        186,
                        196,
                        190,
                        204,
                        221,
                        224,
                        247,
                        257,
                        258,
                        294,
                        320,
                        345,
                        369,
                        391,
                        412,
                        434,
                        459,
                        489,
                        522,
                        556,
                        592,
                        634,
                        671,
                        725,
                        776,
                        808,
                        829,
                        845,
                        860,
                        869,
                        859,
                        838,
                        818,
                        811,
                        807,
                        800,
                        790,
                        783,
                        812,
                        822,
                        823,
                        822,
                        828,
                        855,
                        865,
                        874,
                        876,
                        881,
                        873,
                        858,
                        851,
                        858,
                        862,
                        867,
                        872,
                        873,
                        870,
                        872,
                        883,
                        897,
                        910,
                        919
                    ]
                },
                "region_attributes": {}
            }
        ]
    }
}