{
    "19_760_157.png2568135": {
        "filename": "19_760_157.png",
        "size": 2568135,
        "file_attributes": {},
        "regions": [
            {
                "shape_attributes": {
                    "name": "polyline",
                    "all_points_x": [
                        711,
                        659,
                        603,
                        552,
                        500,
                        445,
                        389,
                        332,
                        276,
                        220,
                        167,
                        120,
                        83,
                        62,
                        71,
                        70,
                        82,
                        103,
                        121,
                        148,
                        170,
                        195,
                        219,
                        250,
                        282,
                        314,
                        348,
                        385,
                        419,
                        452,
                        497,
                        540,
                        581,
                        623,
                        671,
                        717,
                        766,
                        814,
                        862,
                        909,
                        953,
                        1000,
                        1044,
                        1075,
                        1111,
                        1145,
                        1191,
                        1233,
                        1282,
                        1327,
                        1373,
                        1415,
                        1450,
                        1496,
                        1544,
                        1572,
                        1608,
                        1646,
                        1691,
                        1731,
                        1770,
                        1807,
                        1845,
                        1884,
                        1913,
                        1944,
                        1976,
                        2008,
                        2038,
                        2067,
                        2091,
                        2095,
                        2077,
                        2041,
                        2006,
                        1962,
                        1917,
                        1872,
                        1820,
                        1777,
                        1733,
                        1685,
                        1641,
                        1596,
                        1555,
                        1507,
                        1459,
                        1412,
                        1362,
                        1310,
                        1256,
                        1204,
                        1153,
                        1110,
                        1072,
                        1031,
                        984,
                        934,
                        889,
                        844,
                        791,
                        740
                    ],
                    "all_points_y": [
                        779,
                        776,
                        773,
                        767,
                        761,
                        758,
                        755,
                        751,
                        748,
                        743,
                        735,
                        721,
                        699,
                        659,
                        612,
                        570,
                        529,
                        491,
                        450,
                        417,
                        378,
                        341,
                        304,
                        275,
                        245,
                        216,
                        192,
                        168,
                        140,
                        114,
                        106,
                        92,
                        79,
                        70,
                        70,
                        70,
                        65,
                        62,
                        61,
                        63,
                        68,
                        74,
                        73,
                        103,
                        122,
                        135,
                        130,
                        123,
                        131,
                        137,
                        148,
                        165,
                        187,
                        181,
                        189,
                        218,
                        243,
                        266,
                        276,
                        297,
                        319,
                        343,
                        360,
                        380,
                        412,
                        442,
                        465,
                        494,
                        525,
                        557,
                        594,
                        639,
                        679,
                        704,
                        731,
                        746,
                        754,
                        759,
                        758,
                        746,
                        731,
                        718,
                        703,
                        687,
                        675,
                        664,
                        666,
                        680,
                        690,
                        691,
                        686,
                        684,
                        694,
                        712,
                        731,
                        750,
                        760,
                        765,
                        770,
                        769,
                        775,
                        777
                    ]
                },
                "region_attributes": {}
            }
        ]
    }
}