{
    "20_774_226.png2454564": {
        "filename": "20_774_226.png",
        "size": 2454564,
        "file_attributes": {},
        "regions": [
            {
                "shape_attributes": {
                    "name": "polyline",
                    "all_points_x": [
                        834,
                        786,
                        741,
                        696,
                        650,
                        598,
                        547,
                        494,
                        440,
                        386,
                        336,
                        283,
                        231,
                        182,
                        135,
                        99,
                        66,
                        69,
                        92,
                        117,
                        145,
                        170,
                        196,
                        222,
                        249,
                        276,
                        305,
                        336,
                        362,
                        393,
                        415,
                        445,
                        485,
                        530,
                        572,
                        597,
                        643,
                        685,
                        730,
                        771,
                        815,
                        866,
                        913,
                        956,
                        994,
                        1029,
                        1072,
                        1117,
                        1151,
                        1196,
                        1242,
                        1284,
                        1326,
                        1369,
                        1411,
                        1458,
                        1502,
                        1530,
                        1561,
                        1598,
                        1634,
                        1670,
                        1710,
                        1752,
                        1792,
                        1827,
                        1864,
                        1898,
                        1924,
                        1953,
                        1984,
                        2014,
                        2047,
                        2064,
                        2037,
                        2015,
                        1974,
                        1928,
                        1880,
                        1833,
                        1782,
                        1732,
                        1680,
                        1630,
                        1581,
                        1530,
                        1482,
                        1433,
                        1389,
                        1345,
                        1304,
                        1264,
                        1222,
                        1177,
                        1140,
                        1105,
                        1066,
                        1028,
                        983,
                        938,
                        891,
                        838
                    ],
                    "all_points_y": [
                        748,
                        741,
                        733,
                        721,
                        708,
                        701,
                        699,
                        699,
                        702,
                        707,
                        710,
                        710,
                        705,
                        695,
                        683,
                        660,
                        634,
                        589,
                        553,
                        519,
                        488,
                        455,
                        422,
                        389,
                        356,
                        324,
                        295,
                        267,
                        234,
                        206,
                        170,
                        141,
                        124,
                        114,
                        105,
                        77,
                        70,
                        87,
                        95,
                        82,
                        71,
                        64,
                        64,
                        70,
                        89,
                        95,
                        87,
                        97,
                        122,
                        132,
                        139,
                        140,
                        153,
                        165,
                        178,
                        184,
                        177,
                        208,
                        236,
                        258,
                        281,
                        300,
                        319,
                        336,
                        355,
                        377,
                        399,
                        424,
                        457,
                        487,
                        515,
                        544,
                        570,
                        606,
                        638,
                        673,
                        686,
                        699,
                        708,
                        710,
                        716,
                        717,
                        720,
                        727,
                        733,
                        737,
                        736,
                        728,
                        713,
                        698,
                        680,
                        661,
                        644,
                        643,
                        662,
                        686,
                        703,
                        719,
                        729,
                        733,
                        743,
                        747
                    ]
                },
                "region_attributes": {}
            }
        ]
    }
}