{
    "20_774_281.png3325306": {
        "filename": "20_774_281.png",
        "size": 3325306,
        "file_attributes": {},
        "regions": [
            {
                "shape_attributes": {
                    "name": "polyline",
                    "all_points_x": [
                        1017,
                        966,
                        915,
                        864,
                        815,
                        765,
                        724,
                        668,
                        610,
                        555,
                        492,
                        433,
                        378,
                        325,
                        273,
                        223,
                        167,
                        117,
                        85,
                        60,
                        64,
                        95,
                        114,
                        140,
                        170,
                        201,
                        226,
                        255,
                        284,
                        316,
                        349,
                        385,
                        421,
                        458,
                        501,
                        554,
                        588,
                        636,
                        690,
                        745,
                        801,
                        858,
                        908,
                        962,
                        1021,
                        1075,
                        1112,
                        1151,
                        1196,
                        1244,
                        1298,
                        1345,
                        1389,
                        1441,
                        1498,
                        1542,
                        1591,
                        1642,
                        1697,
                        1752,
                        1789,
                        1827,
                        1870,
                        1917,
                        1965,
                        2016,
                        2063,
                        2106,
                        2145,
                        2191,
                        2231,
                        2266,
                        2290,
                        2316,
                        2338,
                        2324,
                        2284,
                        2237,
                        2184,
                        2125,
                        2067,
                        2007,
                        1944,
                        1887,
                        1828,
                        1769,
                        1718,
                        1668,
                        1616,
                        1563,
                        1516,
                        1473,
                        1427,
                        1380,
                        1335,
                        1285,
                        1235,
                        1183,
                        1132,
                        1081,
                        1028
                    ],
                    "all_points_y": [
                        912,
                        912,
                        904,
                        892,
                        878,
                        863,
                        837,
                        826,
                        817,
                        817,
                        817,
                        813,
                        809,
                        803,
                        794,
                        787,
                        784,
                        767,
                        732,
                        690,
                        637,
                        601,
                        555,
                        513,
                        477,
                        440,
                        398,
                        360,
                        323,
                        287,
                        254,
                        222,
                        191,
                        161,
                        137,
                        133,
                        101,
                        85,
                        86,
                        74,
                        67,
                        61,
                        61,
                        59,
                        63,
                        70,
                        100,
                        128,
                        126,
                        127,
                        140,
                        156,
                        179,
                        186,
                        188,
                        205,
                        207,
                        217,
                        225,
                        223,
                        251,
                        280,
                        304,
                        322,
                        341,
                        357,
                        375,
                        399,
                        427,
                        448,
                        475,
                        507,
                        550,
                        591,
                        636,
                        687,
                        714,
                        733,
                        747,
                        749,
                        746,
                        745,
                        741,
                        731,
                        723,
                        725,
                        738,
                        746,
                        757,
                        770,
                        788,
                        809,
                        828,
                        848,
                        867,
                        877,
                        890,
                        895,
                        897,
                        903,
                        909
                    ]
                },
                "region_attributes": {}
            }
        ]
    }
}